beautilog/__init__.py
beautilog/beauti_logger.py
beautilog/beautilog.ini
beautilog/config.py
beautilog/constants.py
beautilog/custom_handlers.py
beautilog-0.2.2.dist-info/licenses/LICENSE
beautilog-0.2.2.dist-info/METADATA
beautilog-0.2.2.dist-info/WHEEL
beautilog-0.2.2.dist-info/top_level.txt
beautilog-0.2.2.dist-info/RECORD
