Metadata-Version: 2.4
Name: beautilog
Version: 0.2.2
Summary: Beautiful, colorful, and configurable logging for Python
Author: Parth Patil
License: Apache-2.0
Project-URL: Homepage, https://github.com/Parth1811/beautilog
Requires-Python: >=3.6
License-File: LICENSE
Requires-Dist: tqdm==4.66.5
Dynamic: license-file
